{
  "set": "P-A",
  "subtitle": "Vol 1",
  "variants": {
    "normal": {
      "rate_numerator": 1,
      "rate_denominator": 1,
      "slot_count": 1,
      "rarity_rates_by_slot": [
        {
          "RR": {
            "normal": {
              "numerator": 633,
              "denominator": 5000
            }
          },
          "C": {
            "normal": {
              "numerator": 447,
              "denominator": 625
            }
          },
          "R": {
            "normal": {
              "numerator": 791,
              "denominator": 5000
            }
          }
        }
      ],
      "card_rates": {
        "017": [
          {
            "numerator": 149,
            "denominator": 625
          }
        ],
        "016": [
          {
            "numerator": 149,
            "denominator": 625
          }
        ],
        "015": [
          {
            "numerator": 149,
            "denominator": 625
          }
        ],
        "014": [
          {
            "numerator": 633,
            "denominator": 5000
          }
        ],
        "013": [
          {
            "numerator": 791,
            "denominator": 5000
          }
        ]
      }
    }
  }
}