{
  "set": "P-A",
  "subtitle": "Vol 9",
  "variants": {
    "normal": {
      "rate": {
        "numerator": 1,
        "denominator": 1
      },
      "slot_count": 1,
      "rarity_rates_by_slot": [
        {
          "C": {
            "normal": {
              "numerator": 3101,
              "denominator": 5000
            }
          },
          "R": {
            "normal": {
              "numerator": 633,
              "denominator": 2500
            }
          },
          "RR": {
            "normal": {
              "numerator": 633,
              "denominator": 5000
            }
          }
        }
      ],
      "card_rates": {
        "080": [
          {
            "numerator": 3101,
            "denominator": 20000
          }
        ],
        "081": [
          {
            "numerator": 633,
            "denominator": 5000
          }
        ],
        "078": [
          {
            "numerator": 633,
            "denominator": 5000
          }
        ],
        "076": [
          {
            "numerator": 3101,
            "denominator": 20000
          }
        ],
        "075": [
          {
            "numerator": 3101,
            "denominator": 20000
          }
        ],
        "079": [
          {
            "numerator": 633,
            "denominator": 5000
          }
        ],
        "077": [
          {
            "numerator": 3101,
            "denominator": 20000
          }
        ]
      }
    }
  }
}