{
  "id": 426,
  "name": "Bidoof",
  "card_type": "pokemon",
  "natdex_number": 399,
  "element": "Colorless",
  "stage": "Basic",
  "hp": 60,
  "retreat_cost": 2,
  "weakness": "Fighting",
  "flavor": "With nerves of steel, nothing can perturb it. It is more agile and active than it appears.",
  "is_ex": false,
  "is_mega": false,
  "attacks": [
    {
      "name": "Super Fang",
      "cost": [
        "Colorless",
        "Colorless"
      ],
      "damage": 0,
      "effect": "Halve your opponent's Active Pokémon's remaining HP, rounded down."
    }
  ],
  "versions": [
    {
      "set": "A2",
      "number": 135
    },
    {
      "set": "A2",
      "number": 177
    },
    {
      "set": "B1",
      "number": 316
    }
  ]
}