{
  "id": 1353,
  "name": "Burmy",
  "card_type": "pokemon",
  "natdex_number": 412,
  "element": "Grass",
  "stage": "Basic",
  "hp": 60,
  "retreat_cost": 1,
  "weakness": "Fire",
  "flavor": "If its cloak is broken in battle, it quickly remakes the cloak with materials nearby.",
  "is_ex": false,
  "is_mega": false,
  "attacks": [
    {
      "name": "Hang Down",
      "cost": [
        "Colorless",
        "Colorless"
      ],
      "damage": 30
    }
  ],
  "versions": [
    {
      "set": "B1a",
      "number": 9
    }
  ]
}