{
  "id": 1730,
  "name": "Tangrowth",
  "card_type": "pokemon",
  "natdex_number": 465,
  "element": "Grass",
  "stage": "Stage 1",
  "hp": 130,
  "retreat_cost": 3,
  "weakness": "Fire",
  "flavor": "Vine growth is accelerated for Tangrowth living in warm climates. If the vines grow long, Tangrowth shortens them by tearing parts of them off.",
  "is_ex": false,
  "is_mega": false,
  "attacks": [
    {
      "name": "Vine Whip",
      "cost": [
        "Grass",
        "Grass",
        "Colorless"
      ],
      "damage": 80
    }
  ],
  "evolves_from": "Tangela",
  "versions": [
    {
      "set": "B3",
      "number": 2
    }
  ]
}