{
  "id": 987,
  "name": "Donphan ex",
  "card_type": "pokemon",
  "natdex_number": 232,
  "element": "Fighting",
  "stage": "Stage 1",
  "hp": 160,
  "retreat_cost": 3,
  "weakness": "Grass",
  "is_ex": true,
  "is_mega": false,
  "attacks": [
    {
      "name": "Gigantic Press",
      "cost": [
        "Fighting"
      ],
      "damage": 50,
      "damage_suffix": "+",
      "effect": "If this Pokémon has at least 2 extra [F] Energy attached, this attack does 60 more damage."
    }
  ],
  "evolves_from": "Phanpy",
  "versions": [
    {
      "set": "A4",
      "number": 100
    },
    {
      "set": "A4",
      "number": 191
    },
    {
      "set": "A4",
      "number": 206
    },
    {
      "set": "A4b",
      "number": 202
    },
    {
      "set": "B2",
      "number": 230
    }
  ]
}