{
  "id": 1109,
  "name": "Ursaring",
  "card_type": "pokemon",
  "natdex_number": 217,
  "element": "Colorless",
  "stage": "Stage 1",
  "hp": 130,
  "retreat_cost": 3,
  "weakness": "Fighting",
  "flavor": "It usually wears a hardened expression, but when it’s licking up honey—which it loves—the joy it feels will cause it to break into a wide grin.",
  "is_ex": false,
  "is_mega": false,
  "attacks": [
    {
      "name": "Claw Slash",
      "cost": [
        "Colorless",
        "Colorless",
        "Colorless",
        "Colorless"
      ],
      "damage": 110
    }
  ],
  "evolves_from": "Teddiursa",
  "versions": [
    {
      "set": "A4a",
      "number": 61
    }
  ]
}