{
  "id": 1146,
  "name": "Thwackey",
  "card_type": "pokemon",
  "natdex_number": 811,
  "element": "Grass",
  "stage": "Stage 1",
  "hp": 90,
  "retreat_cost": 2,
  "weakness": "Fire",
  "flavor": "When it’s drumming out rapid beats in battle, it gets so caught up in the rhythm that it won’t even notice that it’s already knocked out its opponent.",
  "is_ex": false,
  "is_mega": false,
  "attacks": [
    {
      "name": "Hammer In",
      "cost": [
        "Grass",
        "Grass"
      ],
      "damage": 50
    }
  ],
  "evolves_from": "Grookey",
  "versions": [
    {
      "set": "B1",
      "number": 26
    }
  ]
}