{
  "id": 1604,
  "name": "Baxcalibur",
  "card_type": "pokemon",
  "natdex_number": 998,
  "element": "Water",
  "stage": "Stage 2",
  "hp": 140,
  "retreat_cost": 3,
  "weakness": "Metal",
  "flavor": "It launches itself into battle by flipping upside down and spewing frigid air from its mouth. It finishes opponents off with its dorsal blade.",
  "is_ex": false,
  "is_mega": false,
  "ability": {
    "name": "Ice Maker",
    "effect": "Once during your turn, you may take a [Water] Energy from your Energy Zone and attach it to the [Water] Pokémon in the Active Spot."
  },
  "attacks": [
    {
      "name": "Buster Tail",
      "cost": [
        "Water",
        "Water",
        "Water"
      ],
      "damage": 90
    }
  ],
  "evolves_from": "Arctibax",
  "versions": [
    {
      "set": "B2a",
      "number": 36
    },
    {
      "set": "B2a",
      "number": 130
    }
  ]
}