{
  "id": 1778,
  "name": "Inteleon",
  "card_type": "pokemon",
  "natdex_number": 818,
  "element": "Water",
  "stage": "Stage 2",
  "hp": 150,
  "retreat_cost": 2,
  "weakness": "Lightning",
  "flavor": "It may present itself as being well-mannered, but deep down, it still has a lazy side. It will slack off when its Trainer isn’t looking.",
  "is_ex": false,
  "is_mega": false,
  "ability": {
    "name": "Swift Shot",
    "effect": "Once during your turn, when you play this Pokémon from your hand to evolve 1 of your Pokémon, you may do 30 damage to your opponent's Active Pokémon."
  },
  "attacks": [
    {
      "name": "Aqua Edge",
      "cost": [
        "Water",
        "Water"
      ],
      "damage": 70
    }
  ],
  "evolves_from": "Drizzile",
  "versions": [
    {
      "set": "B3",
      "number": 50
    }
  ]
}