{
  "id": 1820,
  "name": "Rolycoly",
  "card_type": "pokemon",
  "natdex_number": 837,
  "element": "Fighting",
  "stage": "Basic",
  "hp": 80,
  "retreat_cost": 3,
  "weakness": "Grass",
  "flavor": "Chunks of the surface of this Pokémon’s body that have grown old and flaked off have long been used for fuel as an alternative to coal.",
  "is_ex": false,
  "is_mega": false,
  "attacks": [
    {
      "name": "Rolling Tackle",
      "cost": [
        "Fighting"
      ],
      "damage": 20
    }
  ],
  "versions": [
    {
      "set": "B3",
      "number": 92
    }
  ]
}