{
  "set": "A2",
  "subtitle": "Dialga",
  "variants": {
    "normal": {
      "rate_numerator": 1999,
      "rate_denominator": 2000,
      "slot_count": 5,
      "rarity_rates_by_slot": [
        {
          "C": {
            "normal": {
              "numerator": 1,
              "denominator": 1
            }
          }
        },
        {
          "C": {
            "normal": {
              "numerator": 1,
              "denominator": 1
            }
          }
        },
        {
          "C": {
            "normal": {
              "numerator": 1,
              "denominator": 1
            }
          }
        },
        {
          "SR": {
            "normal": {
              "numerator": 1,
              "denominator": 300
            }
          },
          "U": {
            "normal": {
              "numerator": 9,
              "denominator": 10
            }
          },
          "UR": {
            "normal": {
              "numerator": 1,
              "denominator": 2500
            }
          },
          "SAR": {
            "normal": {
              "numerator": 1,
              "denominator": 600
            }
          },
          "R": {
            "normal": {
              "numerator": 1,
              "denominator": 20
            }
          },
          "RR": {
            "normal": {
              "numerator": 833,
              "denominator": 50000
            }
          },
          "AR": {
            "normal": {
              "numerator": 643,
              "denominator": 25000
            }
          },
          "IM": {
            "normal": {
              "numerator": 111,
              "denominator": 50000
            }
          }
        },
        {
          "SAR": {
            "normal": {
              "numerator": 1,
              "denominator": 150
            }
          },
          "SR": {
            "normal": {
              "numerator": 1,
              "denominator": 75
            }
          },
          "R": {
            "normal": {
              "numerator": 1,
              "denominator": 5
            }
          },
          "UR": {
            "normal": {
              "numerator": 1,
              "denominator": 625
            }
          },
          "U": {
            "normal": {
              "numerator": 3,
              "denominator": 5
            }
          },
          "IM": {
            "normal": {
              "numerator": 111,
              "denominator": 12500
            }
          },
          "AR": {
            "normal": {
              "numerator": 643,
              "denominator": 6250
            }
          },
          "RR": {
            "normal": {
              "numerator": 833,
              "denominator": 12500
            }
          }
        }
      ],
      "card_rates": {
        "117": [
          null,
          null,
          null,
          {
            "numerator": 9,
            "denominator": 340
          },
          {
            "numerator": 3,
            "denominator": 170
          }
        ],
        "022": [
          null,
          null,
          null,
          {
            "numerator": 1,
            "denominator": 280
          },
          {
            "numerator": 1,
            "denominator": 70
          }
        ],
        "048": [
          {
            "numerator": 1,
            "denominator": 46
          },
          {
            "numerator": 1,
            "denominator": 46
          },
          {
            "numerator": 1,
            "denominator": 46
          },
          null,
          null
        ],
        "064": [
          null,
          null,
          null,
          {
            "numerator": 9,
            "denominator": 340
          },
          {
            "numerator": 3,
            "denominator": 170
          }
        ],
        "166": [
          null,
          null,
          null,
          {
            "numerator": 643,
            "denominator": 300000
          },
          {
            "numerator": 643,
            "denominator": 75000
          }
        ],
        "202": [
          null,
          null,
          null,
          {
            "numerator": 1,
            "denominator": 2400
          },
          {
            "numerator": 1,
            "denominator": 600
          }
        ],
        "056": [
          {
            "numerator": 1,
            "denominator": 46
          },
          {
            "numerator": 1,
            "denominator": 46
          },
          {
            "numerator": 1,
            "denominator": 46
          },
          null,
          null
        ],
        "068": [
          {
            "numerator": 1,
            "denominator": 46
          },
          {
            "numerator": 1,
            "denominator": 46
          },
          {
            "numerator": 1,
            "denominator": 46
          },
          null,
          null
        ],
        "143": [
          null,
          null,
          null,
          {
            "numerator": 1,
            "denominator": 280
          },
          {
            "numerator": 1,
            "denominator": 70
          }
        ],
        "109": [
          null,
          null,
          null,
          {
            "numerator": 1,
            "denominator": 280
          },
          {
            "numerator": 1,
            "denominator": 70
          }
        ],
        "170": [
          null,
          null,
          null,
          {
            "numerator": 643,
            "denominator": 300000
          },
          {
            "numerator": 643,
            "denominator": 75000
          }
        ],
        "092": [
          null,
          null,
          null,
          {
            "numerator": 1,
            "denominator": 280
          },
          {
            "numerator": 1,
            "denominator": 70
          }
        ],
        "021": [
          {
            "numerator": 1,
            "denominator": 46
          },
          {
            "numerator": 1,
            "denominator": 46
          },
          {
            "numerator": 1,
            "denominator": 46
          },
          null,
          null
        ],
        "111": [
          null,
          null,
          null,
          {
            "numerator": 9,
            "denominator": 340
          },
          {
            "numerator": 3,
            "denominator": 170
          }
        ],
        "135": [
          {
            "numerator": 1,
            "denominator": 46
          },
          {
            "numerator": 1,
            "denominator": 46
          },
          {
            "numerator": 1,
            "denominator": 46
          },
          null,
          null
        ],
        "177": [
          null,
          null,
          null,
          {
            "numerator": 643,
            "denominator": 300000
          },
          {
            "numerator": 643,
            "denominator": 75000
          }
        ],
        "147": [
          null,
          null,
          null,
          {
            "numerator": 9,
            "denominator": 340
          },
          {
            "numerator": 3,
            "denominator": 170
          }
        ],
        "097": [
          null,
          null,
          null,
          {
            "numerator": 9,
            "denominator": 340
          },
          {
            "numerator": 3,
            "denominator": 170
          }
        ],
        "065": [
          null,
          null,
          null,
          {
            "numerator": 1,
            "denominator": 280
          },
          {
            "numerator": 1,
            "denominator": 70
          }
        ],
        "017": [
          {
            "numerator": 1,
            "denominator": 46
          },
          {
            "numerator": 1,
            "denominator": 46
          },
          {
            "numerator": 1,
            "denominator": 46
          },
          null,
          null
        ],
        "116": [
          {
            "numerator": 1,
            "denominator": 46
          },
          {
            "numerator": 1,
            "denominator": 46
          },
          {
            "numerator": 1,
            "denominator": 46
          },
          null,
          null
        ],
        "191": [
          null,
          null,
          null,
          {
            "numerator": 1,
            "denominator": 2400
          },
          {
            "numerator": 1,
            "denominator": 600
          }
        ],
        "188": [
          null,
          null,
          null,
          {
            "numerator": 1,
            "denominator": 2400
          },
          {
            "numerator": 1,
            "denominator": 600
          }
        ],
        "071": [
          null,
          null,
          null,
          {
            "numerator": 9,
            "denominator": 340
          },
          {
            "numerator": 3,
            "denominator": 170
          }
        ],
        "118": [
          null,
          null,
          null,
          {
            "numerator": 9,
            "denominator": 340
          },
          {
            "numerator": 3,
            "denominator": 170
          }
        ],
        "200": [
          null,
          null,
          null,
          {
            "numerator": 1,
            "denominator": 2400
          },
          {
            "numerator": 1,
            "denominator": 600
          }
        ],
        "020": [
          null,
          null,
          null,
          {
            "numerator": 1,
            "denominator": 280
          },
          {
            "numerator": 1,
            "denominator": 70
          }
        ],
        "072": [
          null,
          null,
          null,
          {
            "numerator": 1,
            "denominator": 280
          },
          {
            "numerator": 1,
            "denominator": 70
          }
        ],
        "063": [
          {
            "numerator": 1,
            "denominator": 46
          },
          {
            "numerator": 1,
            "denominator": 46
          },
          {
            "numerator": 1,
            "denominator": 46
          },
          null,
          null
        ],
        "163": [
          null,
          null,
          null,
          {
            "numerator": 643,
            "denominator": 300000
          },
          {
            "numerator": 643,
            "denominator": 75000
          }
        ],
        "120": [
          null,
          null,
          null,
          {
            "numerator": 1,
            "denominator": 280
          },
          {
            "numerator": 1,
            "denominator": 70
          }
        ],
        "100": [
          {
            "numerator": 1,
            "denominator": 46
          },
          {
            "numerator": 1,
            "denominator": 46
          },
          {
            "numerator": 1,
            "denominator": 46
          },
          null,
          null
        ],
        "108": [
          null,
          null,
          null,
          {
            "numerator": 9,
            "denominator": 340
          },
          {
            "numerator": 3,
            "denominator": 170
          }
        ],
        "173": [
          null,
          null,
          null,
          {
            "numerator": 643,
            "denominator": 300000
          },
          {
            "numerator": 643,
            "denominator": 75000
          }
        ],
        "146": [
          null,
          null,
          null,
          {
            "numerator": 9,
            "denominator": 340
          },
          {
            "numerator": 3,
            "denominator": 170
          }
        ],
        "179": [
          null,
          null,
          null,
          {
            "numerator": 643,
            "denominator": 300000
          },
          {
            "numerator": 643,
            "denominator": 75000
          }
        ],
        "007": [
          null,
          null,
          null,
          {
            "numerator": 833,
            "denominator": 250000
          },
          {
            "numerator": 833,
            "denominator": 62500
          }
        ],
        "043": [
          null,
          null,
          null,
          {
            "numerator": 9,
            "denominator": 340
          },
          {
            "numerator": 3,
            "denominator": 170
          }
        ],
        "157": [
          null,
          null,
          null,
          {
            "numerator": 643,
            "denominator": 300000
          },
          {
            "numerator": 643,
            "denominator": 75000
          }
        ],
        "153": [
          null,
          null,
          null,
          {
            "numerator": 9,
            "denominator": 340
          },
          {
            "numerator": 3,
            "denominator": 170
          }
        ],
        "015": [
          {
            "numerator": 1,
            "denominator": 46
          },
          {
            "numerator": 1,
            "denominator": 46
          },
          {
            "numerator": 1,
            "denominator": 46
          },
          null,
          null
        ],
        "105": [
          {
            "numerator": 1,
            "denominator": 46
          },
          {
            "numerator": 1,
            "denominator": 46
          },
          {
            "numerator": 1,
            "denominator": 46
          },
          null,
          null
        ],
        "156": [
          null,
          null,
          null,
          {
            "numerator": 643,
            "denominator": 300000
          },
          {
            "numerator": 643,
            "denominator": 75000
          }
        ],
        "089": [
          null,
          null,
          null,
          {
            "numerator": 1,
            "denominator": 280
          },
          {
            "numerator": 1,
            "denominator": 70
          }
        ],
        "119": [
          null,
          null,
          null,
          {
            "numerator": 833,
            "denominator": 250000
          },
          {
            "numerator": 833,
            "denominator": 62500
          }
        ],
        "059": [
          null,
          null,
          null,
          {
            "numerator": 9,
            "denominator": 340
          },
          {
            "numerator": 3,
            "denominator": 170
          }
        ],
        "018": [
          null,
          null,
          null,
          {
            "numerator": 9,
            "denominator": 340
          },
          {
            "numerator": 3,
            "denominator": 170
          }
        ],
        "083": [
          {
            "numerator": 1,
            "denominator": 46
          },
          {
            "numerator": 1,
            "denominator": 46
          },
          {
            "numerator": 1,
            "denominator": 46
          },
          null,
          null
        ],
        "088": [
          null,
          null,
          null,
          {
            "numerator": 9,
            "denominator": 340
          },
          {
            "numerator": 3,
            "denominator": 170
          }
        ],
        "084": [
          null,
          null,
          null,
          {
            "numerator": 9,
            "denominator": 340
          },
          {
            "numerator": 3,
            "denominator": 170
          }
        ],
        "039": [
          null,
          null,
          null,
          {
            "numerator": 9,
            "denominator": 340
          },
          {
            "numerator": 3,
            "denominator": 170
          }
        ],
        "101": [
          null,
          null,
          null,
          {
            "numerator": 9,
            "denominator": 340
          },
          {
            "numerator": 3,
            "denominator": 170
          }
        ],
        "038": [
          {
            "numerator": 1,
            "denominator": 46
          },
          {
            "numerator": 1,
            "denominator": 46
          },
          {
            "numerator": 1,
            "denominator": 46
          },
          null,
          null
        ],
        "138": [
          {
            "numerator": 1,
            "denominator": 46
          },
          {
            "numerator": 1,
            "denominator": 46
          },
          {
            "numerator": 1,
            "denominator": 46
          },
          null,
          null
        ],
        "060": [
          null,
          null,
          null,
          {
            "numerator": 1,
            "denominator": 280
          },
          {
            "numerator": 1,
            "denominator": 70
          }
        ],
        "044": [
          {
            "numerator": 1,
            "denominator": 46
          },
          {
            "numerator": 1,
            "denominator": 46
          },
          {
            "numerator": 1,
            "denominator": 46
          },
          null,
          null
        ],
        "160": [
          null,
          null,
          null,
          {
            "numerator": 643,
            "denominator": 300000
          },
          {
            "numerator": 643,
            "denominator": 75000
          }
        ],
        "069": [
          {
            "numerator": 1,
            "denominator": 46
          },
          {
            "numerator": 1,
            "denominator": 46
          },
          {
            "numerator": 1,
            "denominator": 46
          },
          null,
          null
        ],
        "061": [
          null,
          null,
          null,
          {
            "numerator": 833,
            "denominator": 250000
          },
          {
            "numerator": 833,
            "denominator": 62500
          }
        ],
        "054": [
          {
            "numerator": 1,
            "denominator": 46
          },
          {
            "numerator": 1,
            "denominator": 46
          },
          {
            "numerator": 1,
            "denominator": 46
          },
          null,
          null
        ],
        "206": [
          null,
          null,
          null,
          {
            "numerator": 1,
            "denominator": 5000
          },
          {
            "numerator": 1,
            "denominator": 1250
          }
        ],
        "075": [
          null,
          null,
          null,
          {
            "numerator": 9,
            "denominator": 340
          },
          {
            "numerator": 3,
            "denominator": 170
          }
        ],
        "110": [
          null,
          null,
          null,
          {
            "numerator": 833,
            "denominator": 250000
          },
          {
            "numerator": 833,
            "denominator": 62500
          }
        ],
        "151": [
          null,
          null,
          null,
          {
            "numerator": 9,
            "denominator": 340
          },
          {
            "numerator": 3,
            "denominator": 170
          }
        ],
        "112": [
          null,
          null,
          null,
          {
            "numerator": 9,
            "denominator": 340
          },
          {
            "numerator": 3,
            "denominator": 170
          }
        ],
        "033": [
          null,
          null,
          null,
          {
            "numerator": 1,
            "denominator": 280
          },
          {
            "numerator": 1,
            "denominator": 70
          }
        ],
        "074": [
          null,
          null,
          null,
          {
            "numerator": 9,
            "denominator": 340
          },
          {
            "numerator": 3,
            "denominator": 170
          }
        ],
        "131": [
          {
            "numerator": 1,
            "denominator": 46
          },
          {
            "numerator": 1,
            "denominator": 46
          },
          {
            "numerator": 1,
            "denominator": 46
          },
          null,
          null
        ],
        "058": [
          {
            "numerator": 1,
            "denominator": 46
          },
          {
            "numerator": 1,
            "denominator": 46
          },
          {
            "numerator": 1,
            "denominator": 46
          },
          null,
          null
        ],
        "107": [
          {
            "numerator": 1,
            "denominator": 46
          },
          {
            "numerator": 1,
            "denominator": 46
          },
          {
            "numerator": 1,
            "denominator": 46
          },
          null,
          null
        ],
        "045": [
          null,
          null,
          null,
          {
            "numerator": 9,
            "denominator": 340
          },
          {
            "numerator": 3,
            "denominator": 170
          }
        ],
        "005": [
          null,
          null,
          null,
          {
            "numerator": 9,
            "denominator": 340
          },
          {
            "numerator": 3,
            "denominator": 170
          }
        ],
        "091": [
          {
            "numerator": 1,
            "denominator": 46
          },
          {
            "numerator": 1,
            "denominator": 46
          },
          {
            "numerator": 1,
            "denominator": 46
          },
          null,
          null
        ],
        "090": [
          {
            "numerator": 1,
            "denominator": 46
          },
          {
            "numerator": 1,
            "denominator": 46
          },
          {
            "numerator": 1,
            "denominator": 46
          },
          null,
          null
        ],
        "106": [
          null,
          null,
          null,
          {
            "numerator": 9,
            "denominator": 340
          },
          {
            "numerator": 3,
            "denominator": 170
          }
        ],
        "002": [
          {
            "numerator": 1,
            "denominator": 46
          },
          {
            "numerator": 1,
            "denominator": 46
          },
          {
            "numerator": 1,
            "denominator": 46
          },
          null,
          null
        ],
        "174": [
          null,
          null,
          null,
          {
            "numerator": 643,
            "denominator": 300000
          },
          {
            "numerator": 643,
            "denominator": 75000
          }
        ],
        "194": [
          null,
          null,
          null,
          {
            "numerator": 1,
            "denominator": 2400
          },
          {
            "numerator": 1,
            "denominator": 600
          }
        ],
        "096": [
          {
            "numerator": 1,
            "denominator": 46
          },
          {
            "numerator": 1,
            "denominator": 46
          },
          {
            "numerator": 1,
            "denominator": 46
          },
          null,
          null
        ],
        "008": [
          {
            "numerator": 1,
            "denominator": 46
          },
          {
            "numerator": 1,
            "denominator": 46
          },
          {
            "numerator": 1,
            "denominator": 46
          },
          null,
          null
        ],
        "159": [
          null,
          null,
          null,
          {
            "numerator": 643,
            "denominator": 300000
          },
          {
            "numerator": 643,
            "denominator": 75000
          }
        ],
        "025": [
          {
            "numerator": 1,
            "denominator": 46
          },
          {
            "numerator": 1,
            "denominator": 46
          },
          {
            "numerator": 1,
            "denominator": 46
          },
          null,
          null
        ],
        "026": [
          null,
          null,
          null,
          {
            "numerator": 9,
            "denominator": 340
          },
          {
            "numerator": 3,
            "denominator": 170
          }
        ],
        "031": [
          {
            "numerator": 1,
            "denominator": 46
          },
          {
            "numerator": 1,
            "denominator": 46
          },
          {
            "numerator": 1,
            "denominator": 46
          },
          null,
          null
        ],
        "193": [
          null,
          null,
          null,
          {
            "numerator": 1,
            "denominator": 2400
          },
          {
            "numerator": 1,
            "denominator": 600
          }
        ],
        "009": [
          null,
          null,
          null,
          {
            "numerator": 9,
            "denominator": 340
          },
          {
            "numerator": 3,
            "denominator": 170
          }
        ],
        "076": [
          null,
          null,
          null,
          {
            "numerator": 1,
            "denominator": 280
          },
          {
            "numerator": 1,
            "denominator": 70
          }
        ],
        "185": [
          null,
          null,
          null,
          {
            "numerator": 1,
            "denominator": 2400
          },
          {
            "numerator": 1,
            "denominator": 600
          }
        ],
        "053": [
          null,
          null,
          null,
          {
            "numerator": 1,
            "denominator": 280
          },
          {
            "numerator": 1,
            "denominator": 70
          }
        ],
        "087": [
          null,
          null,
          null,
          {
            "numerator": 9,
            "denominator": 340
          },
          {
            "numerator": 3,
            "denominator": 170
          }
        ],
        "004": [
          {
            "numerator": 1,
            "denominator": 46
          },
          {
            "numerator": 1,
            "denominator": 46
          },
          {
            "numerator": 1,
            "denominator": 46
          },
          null,
          null
        ],
        "051": [
          {
            "numerator": 1,
            "denominator": 46
          },
          {
            "numerator": 1,
            "denominator": 46
          },
          {
            "numerator": 1,
            "denominator": 46
          },
          null,
          null
        ],
        "142": [
          {
            "numerator": 1,
            "denominator": 46
          },
          {
            "numerator": 1,
            "denominator": 46
          },
          {
            "numerator": 1,
            "denominator": 46
          },
          null,
          null
        ],
        "205": [
          null,
          null,
          null,
          {
            "numerator": 111,
            "denominator": 50000
          },
          {
            "numerator": 111,
            "denominator": 12500
          }
        ],
        "052": [
          null,
          null,
          null,
          {
            "numerator": 9,
            "denominator": 340
          },
          {
            "numerator": 3,
            "denominator": 170
          }
        ],
        "102": [
          {
            "numerator": 1,
            "denominator": 46
          },
          {
            "numerator": 1,
            "denominator": 46
          },
          {
            "numerator": 1,
            "denominator": 46
          },
          null,
          null
        ],
        "070": [
          {
            "numerator": 1,
            "denominator": 46
          },
          {
            "numerator": 1,
            "denominator": 46
          },
          {
            "numerator": 1,
            "denominator": 46
          },
          null,
          null
        ],
        "003": [
          null,
          null,
          null,
          {
            "numerator": 9,
            "denominator": 340
          },
          {
            "numerator": 3,
            "denominator": 170
          }
        ],
        "103": [
          null,
          null,
          null,
          {
            "numerator": 9,
            "denominator": 340
          },
          {
            "numerator": 3,
            "denominator": 170
          }
        ],
        "180": [
          null,
          null,
          null,
          {
            "numerator": 1,
            "denominator": 2400
          },
          {
            "numerator": 1,
            "denominator": 600
          }
        ],
        "165": [
          null,
          null,
          null,
          {
            "numerator": 643,
            "denominator": 300000
          },
          {
            "numerator": 643,
            "denominator": 75000
          }
        ],
        "042": [
          {
            "numerator": 1,
            "denominator": 46
          },
          {
            "numerator": 1,
            "denominator": 46
          },
          {
            "numerator": 1,
            "denominator": 46
          },
          null,
          null
        ],
        "095": [
          null,
          null,
          null,
          {
            "numerator": 833,
            "denominator": 250000
          },
          {
            "numerator": 833,
            "denominator": 62500
          }
        ],
        "006": [
          {
            "numerator": 1,
            "denominator": 46
          },
          {
            "numerator": 1,
            "denominator": 46
          },
          {
            "numerator": 1,
            "denominator": 46
          },
          null,
          null
        ],
        "187": [
          null,
          null,
          null,
          {
            "numerator": 1,
            "denominator": 2400
          },
          {
            "numerator": 1,
            "denominator": 600
          }
        ],
        "001": [
          {
            "numerator": 1,
            "denominator": 46
          },
          {
            "numerator": 1,
            "denominator": 46
          },
          {
            "numerator": 1,
            "denominator": 46
          },
          null,
          null
        ],
        "137": [
          {
            "numerator": 1,
            "denominator": 46
          },
          {
            "numerator": 1,
            "denominator": 46
          },
          {
            "numerator": 1,
            "denominator": 46
          },
          null,
          null
        ],
        "196": [
          null,
          null,
          null,
          {
            "numerator": 1,
            "denominator": 2400
          },
          {
            "numerator": 1,
            "denominator": 600
          }
        ],
        "136": [
          {
            "numerator": 1,
            "denominator": 46
          },
          {
            "numerator": 1,
            "denominator": 46
          },
          {
            "numerator": 1,
            "denominator": 46
          },
          null,
          null
        ],
        "144": [
          {
            "numerator": 1,
            "denominator": 46
          },
          {
            "numerator": 1,
            "denominator": 46
          },
          {
            "numerator": 1,
            "denominator": 46
          },
          null,
          null
        ],
        "198": [
          null,
          null,
          null,
          {
            "numerator": 1,
            "denominator": 2400
          },
          {
            "numerator": 1,
            "denominator": 600
          }
        ],
        "073": [
          {
            "numerator": 1,
            "denominator": 46
          },
          {
            "numerator": 1,
            "denominator": 46
          },
          {
            "numerator": 1,
            "denominator": 46
          },
          null,
          null
        ],
        "130": [
          {
            "numerator": 1,
            "denominator": 46
          },
          {
            "numerator": 1,
            "denominator": 46
          },
          {
            "numerator": 1,
            "denominator": 46
          },
          null,
          null
        ],
        "057": [
          null,
          null,
          null,
          {
            "numerator": 1,
            "denominator": 280
          },
          {
            "numerator": 1,
            "denominator": 70
          }
        ],
        "207": [
          null,
          null,
          null,
          {
            "numerator": 1,
            "denominator": 5000
          },
          {
            "numerator": 1,
            "denominator": 1250
          }
        ],
        "016": [
          {
            "numerator": 1,
            "denominator": 46
          },
          {
            "numerator": 1,
            "denominator": 46
          },
          {
            "numerator": 1,
            "denominator": 46
          },
          null,
          null
        ],
        "126": [
          {
            "numerator": 1,
            "denominator": 46
          },
          {
            "numerator": 1,
            "denominator": 46
          },
          {
            "numerator": 1,
            "denominator": 46
          },
          null,
          null
        ],
        "183": [
          null,
          null,
          null,
          {
            "numerator": 1,
            "denominator": 2400
          },
          {
            "numerator": 1,
            "denominator": 600
          }
        ],
        "085": [
          {
            "numerator": 1,
            "denominator": 46
          },
          {
            "numerator": 1,
            "denominator": 46
          },
          {
            "numerator": 1,
            "denominator": 46
          },
          null,
          null
        ],
        "032": [
          null,
          null,
          null,
          {
            "numerator": 9,
            "denominator": 340
          },
          {
            "numerator": 3,
            "denominator": 170
          }
        ],
        "055": [
          null,
          null,
          null,
          {
            "numerator": 9,
            "denominator": 340
          },
          {
            "numerator": 3,
            "denominator": 170
          }
        ],
        "047": [
          {
            "numerator": 1,
            "denominator": 46
          },
          {
            "numerator": 1,
            "denominator": 46
          },
          {
            "numerator": 1,
            "denominator": 46
          },
          null,
          null
        ],
        "030": [
          {
            "numerator": 1,
            "denominator": 46
          },
          {
            "numerator": 1,
            "denominator": 46
          },
          {
            "numerator": 1,
            "denominator": 46
          },
          null,
          null
        ],
        "154": [
          null,
          null,
          null,
          {
            "numerator": 9,
            "denominator": 340
          },
          {
            "numerator": 3,
            "denominator": 170
          }
        ],
        "077": [
          null,
          null,
          null,
          {
            "numerator": 9,
            "denominator": 340
          },
          {
            "numerator": 3,
            "denominator": 170
          }
        ],
        "086": [
          {
            "numerator": 1,
            "denominator": 46
          },
          {
            "numerator": 1,
            "denominator": 46
          },
          {
            "numerator": 1,
            "denominator": 46
          },
          null,
          null
        ]
      }
    },
    "rare": {
      "rate_numerator": 1,
      "rate_denominator": 2000,
      "slot_count": 5,
      "rarity_rates_by_slot": [
        {
          "SAR": {
            "normal": {
              "numerator": 2,
              "denominator": 13
            }
          },
          "SR": {
            "normal": {
              "numerator": 4,
              "denominator": 13
            }
          },
          "IM": {
            "normal": {
              "numerator": 1,
              "denominator": 26
            }
          },
          "AR": {
            "normal": {
              "numerator": 6,
              "denominator": 13
            }
          },
          "UR": {
            "normal": {
              "numerator": 1,
              "denominator": 26
            }
          }
        },
        {
          "AR": {
            "normal": {
              "numerator": 6,
              "denominator": 13
            }
          },
          "SAR": {
            "normal": {
              "numerator": 2,
              "denominator": 13
            }
          },
          "UR": {
            "normal": {
              "numerator": 1,
              "denominator": 26
            }
          },
          "IM": {
            "normal": {
              "numerator": 1,
              "denominator": 26
            }
          },
          "SR": {
            "normal": {
              "numerator": 4,
              "denominator": 13
            }
          }
        },
        {
          "IM": {
            "normal": {
              "numerator": 1,
              "denominator": 26
            }
          },
          "AR": {
            "normal": {
              "numerator": 6,
              "denominator": 13
            }
          },
          "SR": {
            "normal": {
              "numerator": 4,
              "denominator": 13
            }
          },
          "SAR": {
            "normal": {
              "numerator": 2,
              "denominator": 13
            }
          },
          "UR": {
            "normal": {
              "numerator": 1,
              "denominator": 26
            }
          }
        },
        {
          "AR": {
            "normal": {
              "numerator": 6,
              "denominator": 13
            }
          },
          "SAR": {
            "normal": {
              "numerator": 2,
              "denominator": 13
            }
          },
          "IM": {
            "normal": {
              "numerator": 1,
              "denominator": 26
            }
          },
          "SR": {
            "normal": {
              "numerator": 4,
              "denominator": 13
            }
          },
          "UR": {
            "normal": {
              "numerator": 1,
              "denominator": 26
            }
          }
        },
        {
          "AR": {
            "normal": {
              "numerator": 6,
              "denominator": 13
            }
          },
          "UR": {
            "normal": {
              "numerator": 1,
              "denominator": 26
            }
          },
          "SAR": {
            "normal": {
              "numerator": 2,
              "denominator": 13
            }
          },
          "SR": {
            "normal": {
              "numerator": 4,
              "denominator": 13
            }
          },
          "IM": {
            "normal": {
              "numerator": 1,
              "denominator": 26
            }
          }
        }
      ],
      "card_rates": {
        "144": [
          null,
          null,
          null,
          null,
          null
        ],
        "126": [
          null,
          null,
          null,
          null,
          null
        ],
        "146": [
          null,
          null,
          null,
          null,
          null
        ],
        "060": [
          null,
          null,
          null,
          null,
          null
        ],
        "085": [
          null,
          null,
          null,
          null,
          null
        ],
        "160": [
          {
            "numerator": 1,
            "denominator": 26
          },
          {
            "numerator": 1,
            "denominator": 26
          },
          {
            "numerator": 1,
            "denominator": 26
          },
          {
            "numerator": 1,
            "denominator": 26
          },
          {
            "numerator": 1,
            "denominator": 26
          }
        ],
        "194": [
          {
            "numerator": 1,
            "denominator": 26
          },
          {
            "numerator": 1,
            "denominator": 26
          },
          {
            "numerator": 1,
            "denominator": 26
          },
          {
            "numerator": 1,
            "denominator": 26
          },
          {
            "numerator": 1,
            "denominator": 26
          }
        ],
        "187": [
          {
            "numerator": 1,
            "denominator": 26
          },
          {
            "numerator": 1,
            "denominator": 26
          },
          {
            "numerator": 1,
            "denominator": 26
          },
          {
            "numerator": 1,
            "denominator": 26
          },
          {
            "numerator": 1,
            "denominator": 26
          }
        ],
        "090": [
          null,
          null,
          null,
          null,
          null
        ],
        "109": [
          null,
          null,
          null,
          null,
          null
        ],
        "205": [
          {
            "numerator": 1,
            "denominator": 26
          },
          {
            "numerator": 1,
            "denominator": 26
          },
          {
            "numerator": 1,
            "denominator": 26
          },
          {
            "numerator": 1,
            "denominator": 26
          },
          {
            "numerator": 1,
            "denominator": 26
          }
        ],
        "061": [
          null,
          null,
          null,
          null,
          null
        ],
        "097": [
          null,
          null,
          null,
          null,
          null
        ],
        "043": [
          null,
          null,
          null,
          null,
          null
        ],
        "153": [
          null,
          null,
          null,
          null,
          null
        ],
        "064": [
          null,
          null,
          null,
          null,
          null
        ],
        "030": [
          null,
          null,
          null,
          null,
          null
        ],
        "191": [
          {
            "numerator": 1,
            "denominator": 26
          },
          {
            "numerator": 1,
            "denominator": 26
          },
          {
            "numerator": 1,
            "denominator": 26
          },
          {
            "numerator": 1,
            "denominator": 26
          },
          {
            "numerator": 1,
            "denominator": 26
          }
        ],
        "048": [
          null,
          null,
          null,
          null,
          null
        ],
        "044": [
          null,
          null,
          null,
          null,
          null
        ],
        "107": [
          null,
          null,
          null,
          null,
          null
        ],
        "002": [
          null,
          null,
          null,
          null,
          null
        ],
        "156": [
          {
            "numerator": 1,
            "denominator": 26
          },
          {
            "numerator": 1,
            "denominator": 26
          },
          {
            "numerator": 1,
            "denominator": 26
          },
          {
            "numerator": 1,
            "denominator": 26
          },
          {
            "numerator": 1,
            "denominator": 26
          }
        ],
        "142": [
          null,
          null,
          null,
          null,
          null
        ],
        "004": [
          null,
          null,
          null,
          null,
          null
        ],
        "130": [
          null,
          null,
          null,
          null,
          null
        ],
        "032": [
          null,
          null,
          null,
          null,
          null
        ],
        "131": [
          null,
          null,
          null,
          null,
          null
        ],
        "072": [
          null,
          null,
          null,
          null,
          null
        ],
        "120": [
          null,
          null,
          null,
          null,
          null
        ],
        "180": [
          {
            "numerator": 1,
            "denominator": 26
          },
          {
            "numerator": 1,
            "denominator": 26
          },
          {
            "numerator": 1,
            "denominator": 26
          },
          {
            "numerator": 1,
            "denominator": 26
          },
          {
            "numerator": 1,
            "denominator": 26
          }
        ],
        "057": [
          null,
          null,
          null,
          null,
          null
        ],
        "105": [
          null,
          null,
          null,
          null,
          null
        ],
        "076": [
          null,
          null,
          null,
          null,
          null
        ],
        "177": [
          {
            "numerator": 1,
            "denominator": 26
          },
          {
            "numerator": 1,
            "denominator": 26
          },
          {
            "numerator": 1,
            "denominator": 26
          },
          {
            "numerator": 1,
            "denominator": 26
          },
          {
            "numerator": 1,
            "denominator": 26
          }
        ],
        "003": [
          null,
          null,
          null,
          null,
          null
        ],
        "025": [
          null,
          null,
          null,
          null,
          null
        ],
        "042": [
          null,
          null,
          null,
          null,
          null
        ],
        "033": [
          null,
          null,
          null,
          null,
          null
        ],
        "058": [
          null,
          null,
          null,
          null,
          null
        ],
        "193": [
          {
            "numerator": 1,
            "denominator": 26
          },
          {
            "numerator": 1,
            "denominator": 26
          },
          {
            "numerator": 1,
            "denominator": 26
          },
          {
            "numerator": 1,
            "denominator": 26
          },
          {
            "numerator": 1,
            "denominator": 26
          }
        ],
        "039": [
          null,
          null,
          null,
          null,
          null
        ],
        "088": [
          null,
          null,
          null,
          null,
          null
        ],
        "026": [
          null,
          null,
          null,
          null,
          null
        ],
        "077": [
          null,
          null,
          null,
          null,
          null
        ],
        "045": [
          null,
          null,
          null,
          null,
          null
        ],
        "053": [
          null,
          null,
          null,
          null,
          null
        ],
        "166": [
          {
            "numerator": 1,
            "denominator": 26
          },
          {
            "numerator": 1,
            "denominator": 26
          },
          {
            "numerator": 1,
            "denominator": 26
          },
          {
            "numerator": 1,
            "denominator": 26
          },
          {
            "numerator": 1,
            "denominator": 26
          }
        ],
        "206": [
          null,
          null,
          null,
          null,
          null
        ],
        "087": [
          null,
          null,
          null,
          null,
          null
        ],
        "015": [
          null,
          null,
          null,
          null,
          null
        ],
        "006": [
          null,
          null,
          null,
          null,
          null
        ],
        "070": [
          null,
          null,
          null,
          null,
          null
        ],
        "071": [
          null,
          null,
          null,
          null,
          null
        ],
        "116": [
          null,
          null,
          null,
          null,
          null
        ],
        "136": [
          null,
          null,
          null,
          null,
          null
        ],
        "084": [
          null,
          null,
          null,
          null,
          null
        ],
        "163": [
          {
            "numerator": 1,
            "denominator": 26
          },
          {
            "numerator": 1,
            "denominator": 26
          },
          {
            "numerator": 1,
            "denominator": 26
          },
          {
            "numerator": 1,
            "denominator": 26
          },
          {
            "numerator": 1,
            "denominator": 26
          }
        ],
        "207": [
          {
            "numerator": 1,
            "denominator": 26
          },
          {
            "numerator": 1,
            "denominator": 26
          },
          {
            "numerator": 1,
            "denominator": 26
          },
          {
            "numerator": 1,
            "denominator": 26
          },
          {
            "numerator": 1,
            "denominator": 26
          }
        ],
        "069": [
          null,
          null,
          null,
          null,
          null
        ],
        "200": [
          {
            "numerator": 1,
            "denominator": 26
          },
          {
            "numerator": 1,
            "denominator": 26
          },
          {
            "numerator": 1,
            "denominator": 26
          },
          {
            "numerator": 1,
            "denominator": 26
          },
          {
            "numerator": 1,
            "denominator": 26
          }
        ],
        "005": [
          null,
          null,
          null,
          null,
          null
        ],
        "151": [
          null,
          null,
          null,
          null,
          null
        ],
        "102": [
          null,
          null,
          null,
          null,
          null
        ],
        "188": [
          {
            "numerator": 1,
            "denominator": 26
          },
          {
            "numerator": 1,
            "denominator": 26
          },
          {
            "numerator": 1,
            "denominator": 26
          },
          {
            "numerator": 1,
            "denominator": 26
          },
          {
            "numerator": 1,
            "denominator": 26
          }
        ],
        "119": [
          null,
          null,
          null,
          null,
          null
        ],
        "038": [
          null,
          null,
          null,
          null,
          null
        ],
        "196": [
          {
            "numerator": 1,
            "denominator": 26
          },
          {
            "numerator": 1,
            "denominator": 26
          },
          {
            "numerator": 1,
            "denominator": 26
          },
          {
            "numerator": 1,
            "denominator": 26
          },
          {
            "numerator": 1,
            "denominator": 26
          }
        ],
        "091": [
          null,
          null,
          null,
          null,
          null
        ],
        "108": [
          null,
          null,
          null,
          null,
          null
        ],
        "065": [
          null,
          null,
          null,
          null,
          null
        ],
        "008": [
          null,
          null,
          null,
          null,
          null
        ],
        "001": [
          null,
          null,
          null,
          null,
          null
        ],
        "179": [
          {
            "numerator": 1,
            "denominator": 26
          },
          {
            "numerator": 1,
            "denominator": 26
          },
          {
            "numerator": 1,
            "denominator": 26
          },
          {
            "numerator": 1,
            "denominator": 26
          },
          {
            "numerator": 1,
            "denominator": 26
          }
        ],
        "054": [
          null,
          null,
          null,
          null,
          null
        ],
        "092": [
          null,
          null,
          null,
          null,
          null
        ],
        "198": [
          {
            "numerator": 1,
            "denominator": 26
          },
          {
            "numerator": 1,
            "denominator": 26
          },
          {
            "numerator": 1,
            "denominator": 26
          },
          {
            "numerator": 1,
            "denominator": 26
          },
          {
            "numerator": 1,
            "denominator": 26
          }
        ],
        "095": [
          null,
          null,
          null,
          null,
          null
        ],
        "031": [
          null,
          null,
          null,
          null,
          null
        ],
        "096": [
          null,
          null,
          null,
          null,
          null
        ],
        "007": [
          null,
          null,
          null,
          null,
          null
        ],
        "111": [
          null,
          null,
          null,
          null,
          null
        ],
        "137": [
          null,
          null,
          null,
          null,
          null
        ],
        "183": [
          {
            "numerator": 1,
            "denominator": 26
          },
          {
            "numerator": 1,
            "denominator": 26
          },
          {
            "numerator": 1,
            "denominator": 26
          },
          {
            "numerator": 1,
            "denominator": 26
          },
          {
            "numerator": 1,
            "denominator": 26
          }
        ],
        "047": [
          null,
          null,
          null,
          null,
          null
        ],
        "017": [
          null,
          null,
          null,
          null,
          null
        ],
        "170": [
          {
            "numerator": 1,
            "denominator": 26
          },
          {
            "numerator": 1,
            "denominator": 26
          },
          {
            "numerator": 1,
            "denominator": 26
          },
          {
            "numerator": 1,
            "denominator": 26
          },
          {
            "numerator": 1,
            "denominator": 26
          }
        ],
        "157": [
          {
            "numerator": 1,
            "denominator": 26
          },
          {
            "numerator": 1,
            "denominator": 26
          },
          {
            "numerator": 1,
            "denominator": 26
          },
          {
            "numerator": 1,
            "denominator": 26
          },
          {
            "numerator": 1,
            "denominator": 26
          }
        ],
        "022": [
          null,
          null,
          null,
          null,
          null
        ],
        "056": [
          null,
          null,
          null,
          null,
          null
        ],
        "147": [
          null,
          null,
          null,
          null,
          null
        ],
        "103": [
          null,
          null,
          null,
          null,
          null
        ],
        "159": [
          {
            "numerator": 1,
            "denominator": 26
          },
          {
            "numerator": 1,
            "denominator": 26
          },
          {
            "numerator": 1,
            "denominator": 26
          },
          {
            "numerator": 1,
            "denominator": 26
          },
          {
            "numerator": 1,
            "denominator": 26
          }
        ],
        "138": [
          null,
          null,
          null,
          null,
          null
        ],
        "112": [
          null,
          null,
          null,
          null,
          null
        ],
        "020": [
          null,
          null,
          null,
          null,
          null
        ],
        "135": [
          null,
          null,
          null,
          null,
          null
        ],
        "055": [
          null,
          null,
          null,
          null,
          null
        ],
        "073": [
          null,
          null,
          null,
          null,
          null
        ],
        "063": [
          null,
          null,
          null,
          null,
          null
        ],
        "110": [
          null,
          null,
          null,
          null,
          null
        ],
        "174": [
          {
            "numerator": 1,
            "denominator": 26
          },
          {
            "numerator": 1,
            "denominator": 26
          },
          {
            "numerator": 1,
            "denominator": 26
          },
          {
            "numerator": 1,
            "denominator": 26
          },
          {
            "numerator": 1,
            "denominator": 26
          }
        ],
        "051": [
          null,
          null,
          null,
          null,
          null
        ],
        "086": [
          null,
          null,
          null,
          null,
          null
        ],
        "173": [
          {
            "numerator": 1,
            "denominator": 26
          },
          {
            "numerator": 1,
            "denominator": 26
          },
          {
            "numerator": 1,
            "denominator": 26
          },
          {
            "numerator": 1,
            "denominator": 26
          },
          {
            "numerator": 1,
            "denominator": 26
          }
        ],
        "089": [
          null,
          null,
          null,
          null,
          null
        ],
        "117": [
          null,
          null,
          null,
          null,
          null
        ],
        "021": [
          null,
          null,
          null,
          null,
          null
        ],
        "202": [
          {
            "numerator": 1,
            "denominator": 26
          },
          {
            "numerator": 1,
            "denominator": 26
          },
          {
            "numerator": 1,
            "denominator": 26
          },
          {
            "numerator": 1,
            "denominator": 26
          },
          {
            "numerator": 1,
            "denominator": 26
          }
        ],
        "100": [
          null,
          null,
          null,
          null,
          null
        ],
        "016": [
          null,
          null,
          null,
          null,
          null
        ],
        "165": [
          {
            "numerator": 1,
            "denominator": 26
          },
          {
            "numerator": 1,
            "denominator": 26
          },
          {
            "numerator": 1,
            "denominator": 26
          },
          {
            "numerator": 1,
            "denominator": 26
          },
          {
            "numerator": 1,
            "denominator": 26
          }
        ],
        "154": [
          null,
          null,
          null,
          null,
          null
        ],
        "009": [
          null,
          null,
          null,
          null,
          null
        ],
        "059": [
          null,
          null,
          null,
          null,
          null
        ],
        "083": [
          null,
          null,
          null,
          null,
          null
        ],
        "143": [
          null,
          null,
          null,
          null,
          null
        ],
        "075": [
          null,
          null,
          null,
          null,
          null
        ],
        "052": [
          null,
          null,
          null,
          null,
          null
        ],
        "118": [
          null,
          null,
          null,
          null,
          null
        ],
        "074": [
          null,
          null,
          null,
          null,
          null
        ],
        "185": [
          {
            "numerator": 1,
            "denominator": 26
          },
          {
            "numerator": 1,
            "denominator": 26
          },
          {
            "numerator": 1,
            "denominator": 26
          },
          {
            "numerator": 1,
            "denominator": 26
          },
          {
            "numerator": 1,
            "denominator": 26
          }
        ],
        "068": [
          null,
          null,
          null,
          null,
          null
        ],
        "106": [
          null,
          null,
          null,
          null,
          null
        ],
        "101": [
          null,
          null,
          null,
          null,
          null
        ],
        "018": [
          null,
          null,
          null,
          null,
          null
        ]
      }
    }
  }
}