{
  "set": "P-B",
  "subtitle": "Vol 1",
  "variants": {
    "normal": {
      "rate_numerator": 1,
      "rate_denominator": 1,
      "slot_count": 1,
      "rarity_rates_by_slot": [
        {
          "RR": {
            "numerator": 633,
            "denominator": 5000
          },
          "C": {
            "numerator": 447,
            "denominator": 625
          },
          "R": {
            "numerator": 791,
            "denominator": 5000
          }
        }
      ],
      "card_rates": {
        "003": [
          {
            "numerator": 149,
            "denominator": 625
          }
        ],
        "006": [
          {
            "numerator": 633,
            "denominator": 5000
          }
        ],
        "005": [
          {
            "numerator": 149,
            "denominator": 625
          }
        ],
        "004": [
          {
            "numerator": 791,
            "denominator": 5000
          }
        ],
        "002": [
          {
            "numerator": 149,
            "denominator": 625
          }
        ]
      }
    }
  }
}